okxpy/__init__.py
okxpy/okx.py
okxpy/utils.py
okxpy-0.1.7.dist-info/METADATA
okxpy-0.1.7.dist-info/WHEEL
okxpy-0.1.7.dist-info/licenses/LICENSE.txt
okxpy-0.1.7.dist-info/RECORD
