Metadata-Version: 2.1
Name: okxpy
Version: 0.1.7
Summary: A pip package for a Python wrapper that provides an interface to the OKX API
Project-URL: Homepage, https://github.com/EnkhAmar/okxpy
Project-URL: Bug Tracker, https://github.com/EnkhAmar/okxpy/issues
Author-email: Enkh-Amar Ganbat <amra.developer@gmail.com>
License-File: LICENSE.txt
Classifier: License :: OSI Approved :: MIT License
Classifier: Operating System :: OS Independent
Classifier: Programming Language :: Python :: 3
Requires-Python: >=3.8
Requires-Dist: requests
